{
    "task_id": "fb7b4f784cfde003e2548fdf4e8d6b4f",
    "task": "Open the page with an overview of the submission of releases on Discogs.",
    "final_result_response": "The page \"**Overview Of Submission Guidelines For Releases**\" is now open on Discogs. It is located under **Discogs > Database & Contributing > Database Guidelines** and was posted by Discogs Community Support. The page covers basic guidelines for submitting releases to the Discogs database, including:\n\n- Having the exact release in front of you when entering it\n- Only entering verifiable information with trustworthy sources\n- Properly linking artist and label pages\n- Using Artist Name Variations (ANV)\n- Capitalizing names and titles correctly\n- Following the Quick Start Guide for new contributors",
    "result_status": "success",
    "action_history": [
        "Navigate to https://www.discogs.com/",
        "Click at (1098, 681)",
        "Click at (1098, 681)",
        "Click at (1113, 653)",
        "Click at (1113, 653)",
        "Click at (113, 85)",
        "Click at (110, 357)"
    ],
    "thoughts": [
        "",
        "Let me first handle the cookie banner, then navigate to find the submission overview page.",
        "Let me first handle the cookie banner, then navigate to find the submission overview page.",
        "Let me first handle the cookie banner, then navigate to find the submission overview page.",
        "Let me first handle the cookie banner, then navigate to find the submission overview page.",
        "The cookie banner is now dismissed. Now I need to find the page about submission of releases. This is likely under the \"Explore Discography\" or \"Community\" menu, or possibly in the footer. Let me scroll down to look for relevant links, or I can try to find it through the \"Explore Discography\" dropdown which might have submission-related links.\n\nLet me first check the \"Explore Discography\" dropdown for any submission-related options.",
        "I can see the dropdown menu with relevant options. I can see \"Submission Guidelines\" which would be the overview page for submission of releases. Let me click on it."
    ]
}