{
    "task_id": "79f0bd7df6e685f30f20025cc6755c0a_110325",
    "task": "Show me the list of external hard drives for Mac with a capacity greater than 2TB on Micro Center, sorted by price from lowest to highest.",
    "final_result_response": "I now have all 9 products visible. Let me compile the complete list and present the results.\n\nHere are the **9 external hard drives for Mac with capacity greater than 2TB** on Micro Center, sorted by **price from lowest to highest**:\n\n| # | Product | Capacity | Price | Rating | Stock |\n|---|---------|----------|-------|--------|-------|\n| 1 | Seagate Portable 4TB External Hard Drive Portable HDD (STGX4000400) - Black; For PC Laptop and Mac | 4TB | **$129.99** ~~$138.99~~ | 5.0 ★ | 23 in stock |\n| 2 | LaCie Rugged USB-C 4TB External Hard Drive | 4TB | **$149.99** ~~$159.99~~ | 4.3 ★ | 3 in stock |\n| 3 | WD 4TB My Passport for Mac USB 3.2 Gen 2 (Type-A) External Hard Drive - Blue | 4TB | **$149.99** ~~$175.99~~ | 3.5 ★ | 2 in stock |\n| 4 | Seagate 5TB FireCuda Gaming Hard Drive External Hard Drive - USB 3.2 Gen 1, RGB LED (STKL5000400) | 5TB | **$159.99** | 4.0 ★ | 1 in stock |\n| 5 | WD 5TB My Passport for Mac USB 3.2 (Gen1 Type-A) External Hard Drive - Blue | 5TB | **$164.99** ~~$193.99~~ | 3.6 ★ | 1 in stock |\n| 6 | WD 4TB G-DRIVE ArmorATD Rugged Portable External HDD, USB 3.2 (Gen 1 USB-C) | 4TB | **$189.99** ~~$249.99~~ | 5.0 ★ | 1 in stock |\n| 7 | WD 5TB G-DRIVE ArmorATD Rugged Portable External HDD, USB 3.2 (Gen 1 USB-C) | 5TB | **$209.99** ~~$249.99~~ | 2.3 ★ | 1 in stock |\n| 8 | Sandisk 6TB G-DRIVE ArmorATD Rugged Portable External HDD, USB 3.2 (Gen 1 Type-C) | 6TB | **$239.99** ~~$299.99~~ | N/A | 2 in stock |\n| 9 | Seagate 4TB Rugged SSD4 USB4 External SSD | 4TB | **$619.99** ~~$832.99~~ | N/A | 2 in stock |\n\n**Filters applied:** External Hard Drives for Mac, Capacity: 4TB–5.9TB and 6TB–7.9TB, sorted by Lowest Price. All 9 items are currently in stock at the Santa Clara store.",
    "result_status": "success",
    "action_history": [
        "Navigate to https://www.microcenter.com/",
        "Click at (363, 71)",
        "Type \"external hard drives for Mac\"",
        "Press ENTER",
        "Scroll (delta_x=0, delta_y=400)",
        "Scroll (delta_x=0, delta_y=300)",
        "Click at (70, 509)",
        "Click at (70, 597)",
        "Scroll (delta_x=0, delta_y=-700)",
        "Click at (400, 507)",
        "Click at (373, 578)",
        "Click at (373, 578)",
        "Scroll (delta_x=0, delta_y=350)",
        "Scroll (delta_x=0, delta_y=500)",
        "Scroll (delta_x=0, delta_y=500)"
    ],
    "thoughts": [
        "",
        "I can see the Micro Center homepage. Let me search for external hard drives for Mac.",
        "I can see the Micro Center homepage. Let me search for external hard drives for Mac.",
        "I can see the Micro Center homepage. Let me search for external hard drives for Mac.",
        "I can see 19 results for \"external hard drives for Mac\". I need to find a capacity filter to select drives greater than 2TB. Let me scroll down the left sidebar to find capacity filters.",
        "I can see the CAPACITY filter section at the bottom of the sidebar. Let me scroll down to see the capacity options.",
        "I can see the CAPACITY filter options. I need to select capacities greater than 2TB, which means I should check \"4TB to 5.9TB\" and \"6TB to 7.9TB\". Let me click on those filters.",
        "I've selected the \"4TB to 5.9TB\" filter. Now let me also select \"6TB to 7.9TB\" to include all drives greater than 2TB.",
        "Both capacity filters are now selected (4TB to 5.9TB and 6TB to 7.9TB). Now I need to sort by price from lowest to highest. Let me scroll up to access the sort dropdown.",
        "Now I can see 9 results with the capacity filters applied. I need to change the sort from \"Closest Match\" to \"Price Low to High\". Let me click the sort dropdown.",
        "The sort dropdown is open. I can see the \"Lowest Price\" option. Let me click on it.",
        "The dropdown is still showing. Let me click directly on \"Lowest Price\".",
        "The results are now sorted by \"Lowest Price\" with 9 products found. The filters show \"EXTERNAL HARD DRIVES FOR MAC\", \"4TB TO 5.9TB\", and \"6TB TO 7.9TB\". Let me scroll down to see the product details.",
        "I can see the first 3 products sorted by lowest price. Let me scroll down to see the remaining products.",
        "I can see products 4-6. Let me scroll down more to see the remaining products."
    ]
}